gambling_simulator/__main__.py
gambling_simulator-1.0.2.dist-info/METADATA
gambling_simulator-1.0.2.dist-info/WHEEL
gambling_simulator-1.0.2.dist-info/entry_points.txt
gambling_simulator-1.0.2.dist-info/top_level.txt
gambling_simulator-1.0.2.dist-info/RECORD
