Metadata-Version: 2.4
Name: Gambling-Simulator
Version: 1.0.2
Summary: A gambling simulator.
Author-email: Ivole32 <ivo.theis@posteo.de>
Requires-Python: >=3.11
Requires-Dist: customtkinter==5.2.2
Requires-Dist: dill==0.4.0
